startup_control_mcp/__init__.py
startup_control_mcp/server.py
startup_control_mcp-0.1.2.dist-info/METADATA
startup_control_mcp-0.1.2.dist-info/WHEEL
startup_control_mcp-0.1.2.dist-info/entry_points.txt
startup_control_mcp-0.1.2.dist-info/licenses/LICENSE
startup_control_mcp-0.1.2.dist-info/RECORD
