Metadata-Version: 2.4
Name: startup-control-mcp
Version: 0.1.2
Summary: A powerful cross-platform startup item management tool with MCP support | 强大的跨平台开机启动项管理工具
Project-URL: Homepage, https://github.com/yourusername/startup-control-mcp
Project-URL: Bug Tracker, https://github.com/yourusername/startup-control-mcp/issues
Project-URL: Repository, https://github.com/yourusername/startup-control-mcp
Project-URL: Documentation, https://github.com/yourusername/startup-control-mcp#readme
Author-email: Your Name <your.email@example.com>
Maintainer-email: Your Name <your.email@example.com>
License: MIT
License-File: LICENSE
Keywords: autostart,boot,cross-platform,linux,macos,management,mcp,startup,system,windows
Classifier: Development Status :: 4 - Beta
Classifier: Intended Audience :: Developers
Classifier: Intended Audience :: System Administrators
Classifier: License :: OSI Approved :: MIT License
Classifier: Natural Language :: Chinese (Simplified)
Classifier: Natural Language :: English
Classifier: Operating System :: MacOS
Classifier: Operating System :: Microsoft :: Windows
Classifier: Operating System :: OS Independent
Classifier: Operating System :: POSIX :: Linux
Classifier: Programming Language :: Python :: 3
Classifier: Programming Language :: Python :: 3.10
Classifier: Programming Language :: Python :: 3.11
Classifier: Programming Language :: Python :: 3.12
Classifier: Topic :: System :: Boot
Classifier: Topic :: System :: Systems Administration
Classifier: Topic :: Utilities
Requires-Python: >=3.10
Requires-Dist: fastmcp>=0.1.0
Provides-Extra: dev
Requires-Dist: black>=23.0; extra == 'dev'
Requires-Dist: build>=0.10.0; extra == 'dev'
Requires-Dist: mypy>=1.0; extra == 'dev'
Requires-Dist: pytest-cov>=4.0; extra == 'dev'
Requires-Dist: pytest>=7.0; extra == 'dev'
Requires-Dist: ruff>=0.1.0; extra == 'dev'
Requires-Dist: twine>=4.0.0; extra == 'dev'
